sop_phone/__init__.py
sop_phone/filtersets.py
sop_phone/models.py
sop_phone/navigation.py
sop_phone/search.py
sop_phone/urls.py
sop_phone/utils.py
sop_phone/validators.py
sop_phone/api/__init__.py
sop_phone/api/serializers.py
sop_phone/api/urls.py
sop_phone/api/views.py
sop_phone/api/__pycache__/__init__.cpython-312.pyc
sop_phone/api/__pycache__/serializers.cpython-312.pyc
sop_phone/api/__pycache__/urls.cpython-312.pyc
sop_phone/api/__pycache__/views.cpython-312.pyc
sop_phone/forms/phone_delivery.py
sop_phone/forms/phone_did.py
sop_phone/forms/phone_info.py
sop_phone/forms/phone_maintainer.py
sop_phone/forms/__pycache__/phone_delivery.cpython-312.pyc
sop_phone/forms/__pycache__/phone_did.cpython-312.pyc
sop_phone/forms/__pycache__/phone_info.cpython-312.pyc
sop_phone/forms/__pycache__/phone_maintainer.cpython-312.pyc
sop_phone/migrations/0001_initial.py
sop_phone/migrations/__init__.py
sop_phone/migrations/__pycache__/0001_initial.cpython-312.pyc
sop_phone/migrations/__pycache__/__init__.cpython-312.pyc
sop_phone/tables/phone_delivery.py
sop_phone/tables/phone_did.py
sop_phone/tables/phone_info.py
sop_phone/tables/phone_maintainer.py
sop_phone/tables/__pycache__/phone_delivery.cpython-312.pyc
sop_phone/tables/__pycache__/phone_did.cpython-312.pyc
sop_phone/tables/__pycache__/phone_info.cpython-312.pyc
sop_phone/tables/__pycache__/phone_maintainer.cpython-312.pyc
sop_phone/templates/sop_phone/phonedelivery.html
sop_phone/templates/sop_phone/phonedid.html
sop_phone/templates/sop_phone/phoneinfo.html
sop_phone/templates/sop_phone/phonemaintainer.html
sop_phone/templates/sop_phone/tab/phone_info.html
sop_phone/templates/sop_phone/tab/tab.html
sop_phone/templates/sop_phone/tools/badge.html
sop_phone/templates/sop_phone/tools/breadcrumbs.html
sop_phone/templates/sop_phone/tools/display.html
sop_phone/templates/sop_phone/tools/site.html
sop_phone/templates/sop_phone/tools/table.html
sop_phone/tests/__init__.py
sop_phone/tests/test_compute.py
sop_phone/tests/test_models.py
sop_phone-0.4.2.dist-info/METADATA
sop_phone-0.4.2.dist-info/WHEEL
sop_phone-0.4.2.dist-info/top_level.txt
sop_phone-0.4.2.dist-info/RECORD
