Metadata-Version: 2.1
Name: sop-phone
Version: 0.4.2
Summary: Manage phone informations of each sites.
Author: Leorevoir
Author-email: leo.quinzler@epitech.eu
Classifier: Framework :: Django
Classifier: Programming Language :: Python :: 3
Requires-Dist: phonenumbers
